{
  "error": false,
  "error_message": "",
  "history": [
    {
      "PSYPD": null,
      "SYPD": 15.78,
      "counter": 113,
      "created": "2021-11-15-11:25:35",
      "energy": "16K",
      "finish": "2021-11-15-11:25:50",
      "job_id": 18426778,
      "ncpus": 528,
      "nodes": 11,
      "platform": "marenostrum4",
      "qos": "debug",
      "queue_time": "0:00:01",
      "run_created": "2021-11-12-18:51:16",
      "run_id": 92,
      "run_time": "0:00:15",
      "start": "2021-11-15-11:25:35",
      "status": "COMPLETED",
      "submit": "2021-11-15-11:25:34",
      "wallclock": "00:12"
    },
    {
      "PSYPD": null,
      "SYPD": null,
      "counter": 112,
      "created": "2021-11-12-10:53:08",
      "energy": "327K",
      "finish": "2021-11-12-12:01:49",
      "job_id": 18398085,
      "ncpus": 528,
      "nodes": 11,
      "platform": "marenostrum4",
      "qos": "debug",
      "queue_time": "0:00:00",
      "run_created": "2021-11-12-10:44:40",
      "run_id": 89,
      "run_time": "0:00:00",
      "start": "2021-11-12-11:56:43",
      "status": "WAITING",
      "submit": "2021-11-12-10:53:07",
      "wallclock": "00:12"
    },
    {
      "PSYPD": null,
      "SYPD": null,
      "counter": 111,
      "created": "2021-11-12-10:19:54",
      "energy": "NA",
      "finish": "2021-11-12-10:19:54",
      "job_id": 18397436,
      "ncpus": 68,
      "nodes": 0,
      "platform": "marenostrum4",
      "qos": "debug",
      "queue_time": "0:00:00",
      "run_created": "2021-11-12-10:11:55",
      "run_id": 87,
      "run_time": "0:00:00",
      "start": "2021-11-12-10:19:54",
      "status": "WAITING",
      "submit": "2021-11-12-10:19:54",
      "wallclock": "00:12"
    },
    {
      "PSYPD": null,
      "SYPD": null,
      "counter": 110,
      "created": "2021-11-11-18:17:03",
      "energy": "325K",
      "finish": "2021-11-11-18:22:10",
      "job_id": 18388623,
      "ncpus": 528,
      "nodes": 11,
      "platform": "marenostrum4",
      "qos": "debug",
      "queue_time": "0:00:00",
      "run_created": "2021-11-11-16:54:20",
      "run_id": 84,
      "run_time": "0:00:00",
      "start": "2021-11-11-18:17:05",
      "status": "WAITING",
      "submit": "2021-11-11-18:17:02",
      "wallclock": "00:12"
    },
    {
      "PSYPD": null,
      "SYPD": null,
      "counter": 109,
      "created": "2021-11-04-10:55:53",
      "energy": "16K",
      "finish": "2021-11-04-11:12:27",
      "job_id": 18218921,
      "ncpus": 528,
      "nodes": 11,
      "platform": "marenostrum4",
      "qos": "debug",
      "queue_time": "0:00:00",
      "run_created": "2021-11-03-16:28:38",
      "run_id": 82,
      "run_time": "0:00:00",
      "start": "2021-11-04-11:12:10",
      "status": "WAITING",
      "submit": "2021-11-04-10:55:51",
      "wallclock": "00:12"
    },
    {
      "PSYPD": null,
      "SYPD": null,
      "counter": 108,
      "created": "2021-10-21-10:42:17",
      "energy": "NA",
      "finish": "2021-10-21-10:59:35",
      "job_id": 17951878,
      "ncpus": 528,
      "nodes": 11,
      "platform": "marenostrum4",
      "qos": "debug",
      "queue_time": "0:00:00",
      "run_created": "NA",
      "run_id": null,
      "run_time": "0:00:00",
      "start": "2021-10-21-10:54:27",
      "status": "WAITING",
      "submit": "2021-10-21-10:42:04",
      "wallclock": "00:12"
    },
    {
      "PSYPD": null,
      "SYPD": null,
      "counter": 105,
      "created": "2021-09-28-13:36:40",
      "energy": "6K",
      "finish": "2021-09-28-13:52:04",
      "job_id": 17678871,
      "ncpus": 528,
      "nodes": 11,
      "platform": "marenostrum4",
      "qos": "debug",
      "queue_time": "0:00:00",
      "run_created": "2021-09-28-12:26:20",
      "run_id": 67,
      "run_time": "0:00:00",
      "start": "2021-09-28-13:51:34",
      "status": "WAITING",
      "submit": "2021-09-28-13:36:39",
      "wallclock": "00:12"
    },
    {
      "PSYPD": null,
      "SYPD": null,
      "counter": 104,
      "created": "2021-09-08-11:26:36",
      "energy": "NA",
      "finish": "2021-09-08-11:26:36",
      "job_id": 17410934,
      "ncpus": 68,
      "nodes": 0,
      "platform": "marenostrum4",
      "qos": "debug",
      "queue_time": "0:00:00",
      "run_created": "2021-09-08-10:30:19",
      "run_id": 66,
      "run_time": "0:00:00",
      "start": "2021-09-08-11:26:36",
      "status": "SUBMITTED",
      "submit": "2021-09-08-11:26:36",
      "wallclock": "00:12"
    },
    {
      "PSYPD": null,
      "SYPD": 7.89,
      "counter": 101,
      "created": "2021-08-10-11:44:25",
      "energy": "6K",
      "finish": "2021-08-10-12:05:19",
      "job_id": 16924208,
      "ncpus": 528,
      "nodes": 11,
      "platform": "marenostrum4",
      "qos": "debug",
      "queue_time": "0:20:24",
      "run_created": "2021-08-10-10:36:17",
      "run_id": 63,
      "run_time": "0:00:30",
      "start": "2021-08-10-12:04:49",
      "status": "COMPLETED",
      "submit": "2021-08-10-11:44:25",
      "wallclock": "00:12"
    },
    {
      "PSYPD": null,
      "SYPD": 7.64,
      "counter": 100,
      "created": "2021-08-09-17:15:17",
      "energy": "6K",
      "finish": "2021-08-09-17:16:43",
      "job_id": 16902143,
      "ncpus": 528,
      "nodes": 11,
      "platform": "marenostrum4",
      "qos": "debug",
      "queue_time": "0:00:55",
      "run_created": "2021-08-09-17:03:24",
      "run_id": 62,
      "run_time": "0:00:31",
      "start": "2021-08-09-17:16:12",
      "status": "COMPLETED",
      "submit": "2021-08-09-17:15:17",
      "wallclock": "00:12"
    },
    {
      "PSYPD": null,
      "SYPD": 7.89,
      "counter": 99,
      "created": "2021-08-09-13:40:59",
      "energy": "6K",
      "finish": "2021-08-09-13:55:51",
      "job_id": 16900715,
      "ncpus": 528,
      "nodes": 11,
      "platform": "marenostrum4",
      "qos": "debug",
      "queue_time": "0:14:23",
      "run_created": "2021-08-09-13:29:01",
      "run_id": 61,
      "run_time": "0:00:30",
      "start": "2021-08-09-13:55:21",
      "status": "COMPLETED",
      "submit": "2021-08-09-13:40:58",
      "wallclock": "00:12"
    },
    {
      "PSYPD": null,
      "SYPD": 7.89,
      "counter": 97,
      "created": "2021-08-09-11:32:27",
      "energy": "6K",
      "finish": "2021-08-09-11:34:41",
      "job_id": 16900065,
      "ncpus": 528,
      "nodes": 11,
      "platform": "marenostrum4",
      "qos": "debug",
      "queue_time": "0:01:44",
      "run_created": "2021-08-09-11:17:42",
      "run_id": 59,
      "run_time": "0:00:30",
      "start": "2021-08-09-11:34:11",
      "status": "COMPLETED",
      "submit": "2021-08-09-11:32:27",
      "wallclock": "00:12"
    },
    {
      "PSYPD": null,
      "SYPD": 7.89,
      "counter": 96,
      "created": "2021-08-09-08:43:22",
      "energy": "6K",
      "finish": "2021-08-09-08:43:57",
      "job_id": 16898132,
      "ncpus": 528,
      "nodes": 11,
      "platform": "marenostrum4",
      "qos": "debug",
      "queue_time": "0:00:05",
      "run_created": "2021-08-06-17:57:06",
      "run_id": 58,
      "run_time": "0:00:30",
      "start": "2021-08-09-08:43:27",
      "status": "COMPLETED",
      "submit": "2021-08-09-08:43:22",
      "wallclock": "00:12"
    },
    {
      "PSYPD": null,
      "SYPD": 7.89,
      "counter": 95,
      "created": "2021-08-03-17:28:34",
      "energy": "6K",
      "finish": "2021-08-03-17:52:52",
      "job_id": 16796654,
      "ncpus": 528,
      "nodes": 11,
      "platform": "marenostrum4",
      "qos": "debug",
      "queue_time": "0:23:48",
      "run_created": "2021-08-03-16:27:29",
      "run_id": 57,
      "run_time": "0:00:30",
      "start": "2021-08-03-17:52:22",
      "status": "COMPLETED",
      "submit": "2021-08-03-17:28:34",
      "wallclock": "00:12"
    },
    {
      "PSYPD": null,
      "SYPD": 7.89,
      "counter": 94,
      "created": "2021-07-29-09:26:02",
      "energy": "6K",
      "finish": "2021-07-29-09:27:10",
      "job_id": 16714626,
      "ncpus": 528,
      "nodes": 11,
      "platform": "marenostrum4",
      "qos": "debug",
      "queue_time": "0:00:38",
      "run_created": "2021-07-29-09:12:49",
      "run_id": 56,
      "run_time": "0:00:30",
      "start": "2021-07-29-09:26:40",
      "status": "COMPLETED",
      "submit": "2021-07-29-09:26:02",
      "wallclock": "00:12"
    },
    {
      "PSYPD": null,
      "SYPD": 7.89,
      "counter": 91,
      "created": "2021-07-28-09:35:05",
      "energy": "6K",
      "finish": "2021-07-28-09:36:04",
      "job_id": 16701565,
      "ncpus": 528,
      "nodes": 11,
      "platform": "marenostrum4",
      "qos": "debug",
      "queue_time": "0:00:29",
      "run_created": "2021-07-28-09:24:38",
      "run_id": 50,
      "run_time": "0:00:30",
      "start": "2021-07-28-09:35:34",
      "status": "COMPLETED",
      "submit": "2021-07-28-09:35:05",
      "wallclock": "00:12"
    },
    {
      "PSYPD": null,
      "SYPD": 3.2,
      "counter": 83,
      "created": "2021-07-12-14:38:57",
      "energy": "NA",
      "finish": "2021-07-12-14:48:23",
      "job_id": 16619601,
      "ncpus": 624,
      "nodes": 13,
      "platform": "marenostrum4",
      "qos": "debug",
      "queue_time": "18820 days, 13:43:43",
      "run_created": "2021-07-12-12:27:17",
      "run_id": 39,
      "run_time": "0:01:14",
      "start": "2021-07-12-14:47:09",
      "status": "COMPLETED",
      "submit": "2021-07-12-14:38:57",
      "wallclock": "00:10"
    },
    {
      "PSYPD": null,
      "SYPD": 6.23,
      "counter": 58,
      "created": "2021-06-04-12:04:25",
      "energy": "16K",
      "finish": "2021-06-04-12:20:29",
      "job_id": 16177012,
      "ncpus": 96,
      "nodes": 2,
      "platform": "marenostrum4",
      "qos": "debug",
      "queue_time": "0:15:27",
      "run_created": "2021-06-04-10:54:08",
      "run_id": 18,
      "run_time": "0:00:38",
      "start": "2021-06-04-12:19:51",
      "status": "COMPLETED",
      "submit": "2021-06-04-12:04:24",
      "wallclock": "00:10"
    },
    {
      "PSYPD": null,
      "SYPD": 14.79,
      "counter": 50,
      "created": "2021-05-01-00:56:56",
      "energy": "8K",
      "finish": "2021-05-01-00:59:02",
      "job_id": 15523843,
      "ncpus": 96,
      "nodes": 2,
      "platform": "marenostrum4",
      "qos": "debug",
      "queue_time": "0:01:50",
      "run_created": "2021-04-30-16:05:58",
      "run_id": 13,
      "run_time": "0:00:16",
      "start": "2021-05-01-00:58:46",
      "status": "COMPLETED",
      "submit": "2021-05-01-00:56:56",
      "wallclock": "00:10"
    },
    {
      "PSYPD": null,
      "SYPD": 0.79,
      "counter": 42,
      "created": "2021-04-30-00:41:41",
      "energy": "145K",
      "finish": "2021-04-30-04:24:14",
      "job_id": 15500026,
      "ncpus": 480,
      "nodes": 10,
      "platform": "marenostrum4",
      "qos": "debug",
      "queue_time": "3:37:35",
      "run_created": "2021-04-29-15:11:48",
      "run_id": 12,
      "run_time": "0:04:58",
      "start": "2021-04-30-04:19:16",
      "status": "COMPLETED",
      "submit": "2021-04-30-00:41:41",
      "wallclock": "00:10"
    },
    {
      "PSYPD": null,
      "SYPD": 0.89,
      "counter": 40,
      "created": "2021-04-28-12:52:06",
      "energy": "NA",
      "finish": "2021-04-28-13:22:27",
      "job_id": 15474136,
      "ncpus": 480,
      "nodes": 10,
      "platform": "marenostrum4",
      "qos": "debug",
      "queue_time": "0:25:54",
      "run_created": "2021-04-28-10:08:12",
      "run_id": 11,
      "run_time": "0:04:27",
      "start": "2021-04-28-13:18:00",
      "status": "COMPLETED",
      "submit": "2021-04-28-12:52:06",
      "wallclock": "00:10"
    },
    {
      "PSYPD": null,
      "SYPD": null,
      "counter": 36,
      "created": "2021-04-26-14:05:44",
      "energy": "7K",
      "finish": "2021-04-26-14:18:39",
      "job_id": 15437736,
      "ncpus": 480,
      "nodes": 10,
      "platform": "marenostrum4",
      "qos": "debug",
      "queue_time": "0:17:49",
      "run_created": "2021-04-26-11:30:47",
      "run_id": 10,
      "run_time": "0:00:00",
      "start": "2021-04-26-14:23:33",
      "status": "COMPLETED",
      "submit": "2021-04-26-14:05:44",
      "wallclock": "00:10"
    },
    {
      "PSYPD": null,
      "SYPD": null,
      "counter": 34,
      "created": "2021-04-17-15:52:06",
      "energy": "17K",
      "finish": "2021-04-18-03:58:48",
      "job_id": 15328693,
      "ncpus": 480,
      "nodes": 10,
      "platform": "marenostrum4",
      "qos": "debug",
      "queue_time": "12:10:03",
      "run_created": "2021-04-16-16:42:30",
      "run_id": 9,
      "run_time": "0:00:00",
      "start": "2021-04-18-04:02:09",
      "status": "COMPLETED",
      "submit": "2021-04-17-15:52:06",
      "wallclock": "00:10"
    },
    {
      "PSYPD": null,
      "SYPD": 0.39,
      "counter": 30,
      "created": "2021-03-29-16:50:33",
      "energy": "1120K",
      "finish": "2021-03-29-22:49:39",
      "job_id": 15060771,
      "ncpus": 288,
      "nodes": 6,
      "platform": "marenostrum4",
      "qos": "debug",
      "queue_time": "5:48:58",
      "run_created": "2021-03-29-10:14:00",
      "run_id": 8,
      "run_time": "0:10:08",
      "start": "2021-03-29-22:39:31",
      "status": "COMPLETED",
      "submit": "2021-03-29-16:50:33",
      "wallclock": "00:10"
    },
    {
      "PSYPD": null,
      "SYPD": 236.71,
      "counter": 12,
      "created": "2021-03-26-17:59:08",
      "energy": "NA",
      "finish": "2021-03-26-17:59:09",
      "job_id": 14974325,
      "ncpus": 480,
      "nodes": 10,
      "platform": "marenostrum4",
      "qos": "debug",
      "queue_time": "0:00:00",
      "run_created": "2021-03-26-10:00:22",
      "run_id": 7,
      "run_time": "0:00:01",
      "start": "2021-03-26-17:59:08",
      "status": "COMPLETED",
      "submit": "2021-03-26-17:59:08",
      "wallclock": "00:10"
    },
    {
      "PSYPD": null,
      "SYPD": 236.71,
      "counter": 7,
      "created": "2021-03-26-15:01:11",
      "energy": "NA",
      "finish": "2021-03-26-17:58:59",
      "job_id": 14974325,
      "ncpus": 480,
      "nodes": 10,
      "platform": "marenostrum4",
      "qos": "debug",
      "queue_time": "2:57:47",
      "run_created": "2021-03-26-10:00:22",
      "run_id": 7,
      "run_time": "0:00:01",
      "start": "2021-03-26-17:58:58",
      "status": "COMPLETED",
      "submit": "2021-03-26-15:01:11",
      "wallclock": "00:10"
    },
    {
      "PSYPD": null,
      "SYPD": null,
      "counter": 6,
      "created": "2021-03-26-15:01:02",
      "energy": "NA",
      "finish": "2021-03-26-15:01:02",
      "job_id": 14974325,
      "ncpus": 68,
      "nodes": 0,
      "platform": "marenostrum4",
      "qos": "debug",
      "queue_time": "0:00:00",
      "run_created": "2021-03-26-10:00:22",
      "run_id": 7,
      "run_time": "0:00:00",
      "start": "2021-03-26-15:01:02",
      "status": "SUBMITTED",
      "submit": "2021-03-26-15:01:02",
      "wallclock": "00:10"
    },
    {
      "PSYPD": null,
      "SYPD": 4.55,
      "counter": 4,
      "created": "2021-03-24-15:50:34",
      "energy": "19K",
      "finish": "2021-03-24-16:12:45",
      "job_id": 14922785,
      "ncpus": 96,
      "nodes": 2,
      "platform": "marenostrum4",
      "qos": "debug",
      "queue_time": "0:21:19",
      "run_created": "2021-03-24-12:05:56",
      "run_id": 6,
      "run_time": "0:00:52",
      "start": "2021-03-24-16:11:53",
      "status": "COMPLETED",
      "submit": "2021-03-24-15:50:34",
      "wallclock": "00:10"
    },
    {
      "PSYPD": null,
      "SYPD": 0.38,
      "counter": 2,
      "created": "2021-03-15-14:38:07",
      "energy": "NA",
      "finish": "2021-03-15-15:12:43",
      "job_id": 14765295,
      "ncpus": 480,
      "nodes": 10,
      "platform": "marenostrum4",
      "qos": "debug",
      "queue_time": "0:24:14",
      "run_created": "2021-03-15-13:36:32",
      "run_id": 3,
      "run_time": "0:10:22",
      "start": "2021-03-15-15:02:21",
      "status": "COMPLETED",
      "submit": "2021-03-15-14:38:07",
      "wallclock": "00:10"
    }
  ]
}